pyoe/__init__.py
pyoe/__version__.py
pyoe/preprocessors.py
pyoe/utils.py
pyoe/OEBench/__init__.py
pyoe/OEBench/arf.py
pyoe/OEBench/armnet.py
pyoe/OEBench/cluster.py
pyoe/OEBench/dataset_selection.py
pyoe/OEBench/entmax.py
pyoe/OEBench/ewc.py
pyoe/OEBench/experiments.py
pyoe/OEBench/layers.py
pyoe/OEBench/model.py
pyoe/OEBench/outliers.py
pyoe/OEBench/pipeline.py
pyoe/OEBench/stream_cluster.py
pyoe/OEBench/ADBench/__init__.py
pyoe/OEBench/ADBench/data_generator.py
pyoe/OEBench/ADBench/myutils.py
pyoe/OEBench/ADBench/run.py
pyoe/OEBench/ADBench/baseline/PyOD.py
pyoe/OEBench/ADBench/baseline/Supervised.py
pyoe/OEBench/ADBench/baseline/__init__.py
pyoe/algorithms/__init__.py
pyoe/algorithms/loss.py
pyoe/algorithms/trainer.py
pyoe/dataloaders/__init__.py
pyoe/dataloaders/base.py
pyoe/dataloaders/pipeline.py
pyoe/metrics/__init__.py
pyoe/metrics/metrics.py
pyoe/models/__init__.py
pyoe/models/models.py
pyoe/models/networks.py
pyoe-0.1.2.dist-info/LICENSE
pyoe-0.1.2.dist-info/METADATA
pyoe-0.1.2.dist-info/WHEEL
pyoe-0.1.2.dist-info/top_level.txt
pyoe-0.1.2.dist-info/RECORD
