Metadata-Version: 2.1
Name: pyoe
Version: 0.1.2
Summary: Investigating open environment challenges in real-world relational data streams with PyOE.
Home-page: https://github.com/sjtudyq/PyOE
Author: Liao Chengfan
Author-email: liao_chengfan@sjtu.edu.cn
License: MIT
Platform: UNKNOWN
Classifier: License :: OSI Approved :: MIT License
Classifier: Programming Language :: Python
Classifier: Programming Language :: Python :: 3
Classifier: Programming Language :: Python :: 3.10
Classifier: Programming Language :: Python :: Implementation :: CPython
Classifier: Programming Language :: Python :: Implementation :: PyPy
Requires-Python: >=3.10
License-File: LICENSE
Requires-Dist: Pillow==10.4.0
Requires-Dist: autogluon.timeseries[chronos-openvino]==1.1.1
Requires-Dist: catboost==1.2.5
Requires-Dist: click==8.1.7
Requires-Dist: combo==0.1.3
Requires-Dist: copulas==0.11.0
Requires-Dist: cvxopt==1.3.2
Requires-Dist: delu==0.0.25
Requires-Dist: einops==0.8.0
Requires-Dist: keras==2.15.0
Requires-Dist: lightgbm==4.3.0
Requires-Dist: matplotlib==3.9.2
Requires-Dist: menelaus==0.2.0
Requires-Dist: networkx==3.3
Requires-Dist: numpy==1.23.5
Requires-Dist: pandas==2.2.2
Requires-Dist: pyod==1.1.3
Requires-Dist: pytorch-tabnet==4.1.0
Requires-Dist: scikit-learn==1.4.0
Requires-Dist: scikit-multiflow==0.5.3
Requires-Dist: scipy==1.12.0
Requires-Dist: seaborn==0.13.2
Requires-Dist: tensorflow==2.15.0
Requires-Dist: torch==2.3.1
Requires-Dist: torchvision==0.18.1
Requires-Dist: tqdm==4.66.4
Requires-Dist: wget==3.2
Requires-Dist: xgboost==2.0.3
Provides-Extra: required
Requires-Dist: river==0.21.2; extra == "required"
Requires-Dist: rtdl==0.0.13; extra == "required"
Requires-Dist: streamad==0.3.1; extra == "required"
